odoo/addons/mrp_bom_hierarchy/README.rst
odoo/addons/mrp_bom_hierarchy/__init__.py
odoo/addons/mrp_bom_hierarchy/__manifest__.py
odoo/addons/mrp_bom_hierarchy/i18n/es.po
odoo/addons/mrp_bom_hierarchy/i18n/fr.po
odoo/addons/mrp_bom_hierarchy/i18n/it.po
odoo/addons/mrp_bom_hierarchy/i18n/mrp_bom_hierarchy.pot
odoo/addons/mrp_bom_hierarchy/model/__init__.py
odoo/addons/mrp_bom_hierarchy/model/mrp_bom.py
odoo/addons/mrp_bom_hierarchy/model/mrp_bom_line.py
odoo/addons/mrp_bom_hierarchy/readme/CONTRIBUTORS.md
odoo/addons/mrp_bom_hierarchy/readme/DESCRIPTION.md
odoo/addons/mrp_bom_hierarchy/readme/USAGE.md
odoo/addons/mrp_bom_hierarchy/static/description/icon.png
odoo/addons/mrp_bom_hierarchy/static/description/index.html
odoo/addons/mrp_bom_hierarchy/view/mrp_bom.xml
odoo_addon_mrp_bom_hierarchy-18.0.1.0.1.dist-info/METADATA
odoo_addon_mrp_bom_hierarchy-18.0.1.0.1.dist-info/WHEEL
odoo_addon_mrp_bom_hierarchy-18.0.1.0.1.dist-info/top_level.txt
odoo_addon_mrp_bom_hierarchy-18.0.1.0.1.dist-info/RECORD
